{
  "kind": "singleType",
  "collectionName": "about_uses",
  "info": {
    "singularName": "about-us",
    "pluralName": "about-uses",
    "displayName": "about-us",
    "description": ""
  },
  "options": {
    "draftAndPublish": true
  },
  "pluginOptions": {},
  "attributes": {
    "slug": {
      "type": "string"
    },
    "sections": {
      "type": "dynamiczone",
      "components": [
        "section.richtext",
        "section.image-banner",
        "section.banner-slideshow"
      ]
    }
  }
}
